src/__init__.py
src/main.py
CASTEP_dispersion-1.0.16.dist-info/LICENSE
CASTEP_dispersion-1.0.16.dist-info/METADATA
CASTEP_dispersion-1.0.16.dist-info/WHEEL
CASTEP_dispersion-1.0.16.dist-info/entry_points.txt
CASTEP_dispersion-1.0.16.dist-info/top_level.txt
CASTEP_dispersion-1.0.16.dist-info/RECORD
